{
    "00": [
        {
            "lat": "22.28552", 
            "name": "Hong Kong", 
            "long": "114.15769"
        }
    ], 
    "NTP": [
        {
            "lat": "22.45007", 
            "name": "Tai Po", 
            "long": "114.16877"
        }
    ], 
    "NTW": [
        {
            "lat": "22.37066", 
            "name": "Tsuen Wan", 
            "long": "114.10479"
        }
    ], 
    "NTM": [
        {
            "lat": "22.39175", 
            "name": "Tuen Mun", 
            "long": "113.97157"
        }
    ], 
    "NYL": [
        {
            "lat": "22.45", 
            "name": "Yuen Long Kau Hui", 
            "long": "114.03333"
        }
    ], 
    "NST": [
        {
            "lat": "22.38333", 
            "name": "Sha Tin", 
            "long": "114.18333"
        }
    ], 
    "KKC": [
        {
            "lat": "22.31667", 
            "name": "Kowloon", 
            "long": "114.18333"
        }
    ]
}